mypo/__init__.py
mypo/common.py
mypo/evacuator/__init__.py
mypo/evacuator/base_evacuator.py
mypo/evacuator/calendar_evacuator.py
mypo/evacuator/covariance_evacuator.py
mypo/evacuator/fixed_evacuator.py
mypo/evacuator/moving_average_evacuator.py
mypo/evacuator/no_evacuator.py
mypo/loader.py
mypo/market.py
mypo/model_selection.py
mypo/optimizer/__init__.py
mypo/optimizer/base_optimizer.py
mypo/optimizer/cvar_optimizer.py
mypo/optimizer/maximum_diversification_optimizer.py
mypo/optimizer/mean_variance_optimizer.py
mypo/optimizer/minimum_variance_optimizer.py
mypo/optimizer/no_optimizer.py
mypo/optimizer/risk_parity_optimizer.py
mypo/optimizer/rotation_strategy.py
mypo/optimizer/sharpe_ratio_optimizer.py
mypo/rebalancer/__init__.py
mypo/rebalancer/base_rebalancer.py
mypo/rebalancer/monthly_rebalancer.py
mypo/rebalancer/no_rebalancer.py
mypo/rebalancer/plain_rebalancer.py
mypo/rebalancer/threshold_rebalancer.py
mypo/reporter/__init__.py
mypo/reporter/indicators.py
mypo/reporter/reporter.py
mypo/runner.py
mypo/sampler/__init__.py
mypo/sampler/sampler.py
mypo/settings.py
mypo/trigger/__init__.py
mypo/trigger/always_trigger.py
mypo/trigger/base_trigger.py
mypo/trigger/monthly_trigger.py
mypo/trigger/no_trigger.py
mypo/trigger/threshold_trigger.py
mypo-0.0.85.dist-info/LICENSE
mypo-0.0.85.dist-info/WHEEL
mypo-0.0.85.dist-info/METADATA
mypo-0.0.85.dist-info/RECORD
