Metadata-Version: 2.1
Name: mypo
Version: 0.0.85
Summary: 
Home-page: https://github.com/sonesuke/mypo
License: MIT
Author: sonesuke
Author-email: iamsonesuke@gmail.com
Requires-Python: >=3.7.10,<4.0.0
Classifier: License :: OSI Approved :: MIT License
Classifier: Programming Language :: Python :: 3
Classifier: Programming Language :: Python :: 3.8
Classifier: Programming Language :: Python :: 3.9
Requires-Dist: joblib (>=1.0.1,<2.0.0)
Requires-Dist: numpy (>=1.20.1,<2.0.0)
Requires-Dist: pandas (>=1.2.2,<2.0.0)
Requires-Dist: pymc3 (>=3.11.1,<4.0.0)
Requires-Dist: scipy (>=1.6.0,<2.0.0)
Requires-Dist: tqdm (>=4.59.0,<5.0.0)
Requires-Dist: yfinance (>=0.1.62,<0.2.0)
Project-URL: Repository, https://github.com/sonesuke/mypo
